LICENSE
MANIFEST.in
README.md
setup.py
inventory_monitor/__init__.py
inventory_monitor/helpers.py
inventory_monitor/navigation.py
inventory_monitor/search.py
inventory_monitor/settings.py
inventory_monitor/template_content.py
inventory_monitor/urls.py
inventory_monitor/version.py
inventory_monitor.egg-info/PKG-INFO
inventory_monitor.egg-info/SOURCES.txt
inventory_monitor.egg-info/dependency_links.txt
inventory_monitor.egg-info/not-zip-safe
inventory_monitor.egg-info/top_level.txt
inventory_monitor/api/__init__.py
inventory_monitor/api/serializers.py
inventory_monitor/api/urls.py
inventory_monitor/api/views.py
inventory_monitor/filtersets/__init__.py
inventory_monitor/filtersets/asset.py
inventory_monitor/filtersets/asset_service.py
inventory_monitor/filtersets/asset_type.py
inventory_monitor/filtersets/contract.py
inventory_monitor/filtersets/contractor.py
inventory_monitor/filtersets/external_inventory.py
inventory_monitor/filtersets/invoice.py
inventory_monitor/filtersets/probe.py
inventory_monitor/filtersets/rma.py
inventory_monitor/forms/__init__.py
inventory_monitor/forms/asset.py
inventory_monitor/forms/asset_service.py
inventory_monitor/forms/asset_type.py
inventory_monitor/forms/contract.py
inventory_monitor/forms/contractor.py
inventory_monitor/forms/external_inventory.py
inventory_monitor/forms/invoice.py
inventory_monitor/forms/probe.py
inventory_monitor/forms/rma.py
inventory_monitor/graphql/__init__.py
inventory_monitor/graphql/enums.py
inventory_monitor/graphql/filters.py
inventory_monitor/graphql/schema.py
inventory_monitor/graphql/types.py
inventory_monitor/migrations/0001_initial_squashed.py
inventory_monitor/migrations/0002_alter_asset_options_alter_assetservice_options_and_more.py
inventory_monitor/migrations/0003_assetservice_description_contract_description_and_more.py
inventory_monitor/migrations/0004_alter_asset_tags_alter_assetservice_tags_and_more.py
inventory_monitor/migrations/__init__.py
inventory_monitor/models/__init__.py
inventory_monitor/models/asset.py
inventory_monitor/models/asset_service.py
inventory_monitor/models/asset_type.py
inventory_monitor/models/contract.py
inventory_monitor/models/contractor.py
