Metadata-Version: 2.4
Name: inventory-monitor
Version: 13.0.0
Summary: Asset Management with semi-auto discovery processes
Home-page: https://github.com/CESNET/inventory-monitor-plugin
Author: Jan Krupa
License: Apache-2.0
Keywords: netbox,netbox-plugin
Classifier: Framework :: Django
Classifier: Programming Language :: Python :: 3
Classifier: Programming Language :: Python :: 3.12
Classifier: License :: OSI Approved :: Apache Software License
Requires-Python: >=3.12
License-File: LICENSE
Dynamic: author
Dynamic: classifier
Dynamic: description
Dynamic: description-content-type
Dynamic: home-page
Dynamic: keywords
Dynamic: license
Dynamic: license-file
Dynamic: requires-python
Dynamic: summary
